osmtilecalc/__init__.py
osmtilecalc/calculators.py
osmtilecalc/main.py
osmtilecalc/validators.py
tile_calculator/__init__.py
tile_calculator/calculators.py
tile_calculator/main.py
tile_calculator/validators.py
osmtilecalc-1.0.0.dist-info/LICENSE
osmtilecalc-1.0.0.dist-info/METADATA
osmtilecalc-1.0.0.dist-info/WHEEL
osmtilecalc-1.0.0.dist-info/entry_points.txt
osmtilecalc-1.0.0.dist-info/top_level.txt
osmtilecalc-1.0.0.dist-info/RECORD
