Metadata-Version: 2.1
Name: osmtilecalc
Version: 1.0.0
Summary: Calculates Open Street Map tile coordinates.
Home-page: https://github.com/irzu/osmtilecalc
Author: Irek Żuchowski
Author-email: irek@atarnia.com
License: UNKNOWN
Platform: UNKNOWN
Requires-Dist: setuptools
